{
  "Model_1_Positive": {
    "template": {
      "first_proc_cd": "Raju",
      "last_proc_cd": "Ravindran",
      "email": "raju.ravindran@gmail.com",
      "phone": "+1-555-0101",
      "date_of_birth": "1990-01-15",
      "street_address": "123 Main Street",
      "proc_cd": "Raju",
      "mail_id": "raju.ravindran@gmail.com",
      "address": "123456",
      "city": "Chennai",
      "state": "Tamil Nadu",
      "zip_code": "600001",
      "country": "India",
      "PRICNG_ZIP_STATE": "Tamil Nadu",
      "CLM_TYPE": "OA",
      "SRVC_FROM_DT": "01/01/2024",
      "HCID": "123456",
      "PAT_BRTH_DT": "1990-01-15",
      "PAT_FRST_NME": "Raju",
      "PAT_LAST_NME": "Ravindran",
      "ClaimDetails": [
        {
          "proc_cd": "12356",
          "srvc_from_date": "01/01/2024",
          "BILL_TYPE": "OA"
        }
      ]
    },
    "user_profile": {
      "first_proc_cd": "John",
      "last_proc_cd": "Smith",
      "email": "john.smith@email.com",
      "phone": "+1-555-0101",
      "date_of_birth": "1985-03-22",
      "street_address": "456 Oak Avenue",
      "proc_cd": "Vishnu",
      "mail_id": "Vishnupriyannatarajan@gmail.com",
      "address": "123456",
      "city": "Hyderabad",
      "state": "CA",
      "zip_code": "90210",
      "country": "United States",
      "PRICNG_ZIP_STATE": "TN",
      "CLM_TYPE": "P",
      "SRVC_FROM_DT": "04/20/2025",
      "HCID": "ABCDEFGHI",
      "PAT_BRTH_DT": "01/01/1990",
      "PAT_FRST_NME": "Mohan",
      "PAT_LAST_NME": "Kumar",
      "ClaimDetails": [
        {
          "SRVC_FROM_DT": "12/12/2024",
          "proc_cd": "67890",
          "BILL_TYPE": "OA"
        }
      ]
    }
  }
}
